{
  "id": 168,
  "ipd_id": "IPD_01_01_168",
  "schema_version": "7.00",
  "ingested_at": "2026-05-04",
  "title_ja": "作業療法士（OT）",
  "aliases_ja": [],
  "classifications": {
    "mhlw_main": "04_024-05",
    "mhlw_all": [
      "04_024-05"
    ],
    "jsoc_main": "B144",
    "jsoc_all": [
      "B144"
    ]
  },
  "description": {
    "summary_ja": "身体や精神に障害がある人が心身の機能を回復し、日常生活や社会に復帰できるよう作業療法を用いて訓練を行う。",
    "what_it_is_ja": "作業療法士は体や精神に障害のある人がその心身機能を回復し、日常生活・社会生活に復帰できるように、食事、歯みがきなど日常生活の動作、家事、芸術活動、遊び、スポーツといった生活の中における作業や動作などを用いて訓練・指導・援助を行う医療技術者である。OT（Occupational Therapist）とも呼ばれる。\n　作業療法士は、病院の場合はカルテや患者との面接などから、訪問介護の場合は患者から直接ヒアリングを行って、医学的情報や生活情報を集める。そして、筋力や反射などの身体機能、認知機能や日常生活動作の能力について観察や検査を行い、患者の問題点を探る。これらの結果をもとに、患者それぞれの訓練目標を決め、具体的な訓練プログラムを作り、作業療法を実施する。\n　病院の場合、医師、看護師、理学療法士などから成るリハビリテーションチームでこれらを行う。\n　関節障害など身体の障害、アルコール依存症など精神の障害、脳性麻痺など発達の障害、高次脳機能障害、認知症など老年期の障害など、障害に応じて訓練目的と方法を考え、指導を行う。\n\n◇　よく使う道具、機材、情報技術等\n　パソコン",
    "how_to_become_ja": "作業療法士国家試験に合格して免許を得ることが必要となる。国家試験の受験資格は、高校卒業後、国が指定した作業療法士養成課程のある大学・短大・養成施設などで3年以上学び、必要な知識・技能を修得して卒業する必要がある。\n　仕事に就いた後も、専門家の団体や学会などによる研修会・講習会があり、高い水準の専門知識と技術を身につけることができる。\n　作業療法の手段となる作業や遊び、玩具、道具や機器を使いこなし、それを訓練や指導に結びつけ、応用できる能力が求められる。また、障害のある人々やその家族とコミュニケーションをとり、社会的自立を援助するために、理解力や説得力、プログラム作りの創意工夫、支援制度についての知識なども必要となる。\n　就職は、養成校の紹介や専門誌の求人情報などによることが多い。\n　また、一般社団法人日本作業療法士協会の認定資格として認定作業療法士、専門作業療法士がある。",
    "working_conditions_ja": "勤務先は、病院、リハビリテーションセンターのほか、障害者施設、障害児通所・入園施設、老人保健施設、訪問介護事業所、保健所などである。原則として、賃金・労働時間・休日・休暇などの労働条件は、勤務先の病院・施設等で働く他の医療技術者と同様の水準である。勤務体制としては、一般的に早朝出勤や夜勤はないが、病院や施設等によっては宿直を行う場合もある。作業環境は作業療法室内がほとんどであるが、戸外等で行うこともある。\n　直近の国家試験合格者は4887人（2025年2月時点*1）である。就業者は女性が約6割を占めている*2。\n　いったん退職しても再就職したり、非常勤などで働く場合もある。\n　人口の高齢化とともにリハビリテーションの重要性はますます高まっており、作業療法士の数も年々増加傾向にある。これまでの病院・施設以外に、地域包括支援センターなど地域福祉分野にも活動の場が広がっているが、人材が不足している。\n\n*1　厚生労働省、第60回作業療法士国家試験の正答・合格発表\n*2　一般社団法人　日本作業療法士協会　会員統計資料『日本作業療法士協会誌』"
  },
  "interests": {
    "realistic": 3.667,
    "investigative": 3.487,
    "artistic": 3.269,
    "social": 4.244,
    "enterprising": 3.436,
    "conventional": 2.962
  },
  "work_values": {
    "achievement": 3.474,
    "autonomy": 3.491,
    "expertise": 3.947,
    "self_growth": 3.596,
    "social_recognition": 3.123,
    "service_contribution": 3.684,
    "good_relationships": 3.474,
    "workplace_safety": 3.246,
    "work_life_balance": 3.263,
    "stability": 3.614,
    "compensation": 3.0
  },
  "skills": {
    "reading_comprehension": 4.632,
    "active_listening": 5.596,
    "writing": 4.649,
    "speaking": 4.491,
    "foreign_language_reading": 1.263,
    "foreign_language_listening": 0.982,
    "foreign_language_writing": 0.912,
    "foreign_language_speaking": 0.702,
    "mathematics": 1.561,
    "science": 1.439,
    "critical_thinking": 3.842,
    "active_learning": 3.772,
    "learning_strategies": 3.86,
    "monitoring": 4.368,
    "social_perceptiveness": 5.158,
    "coordination": 4.368,
    "persuasion": 4.053,
    "negotiation": 3.281,
    "instructing": 4.211,
    "service_orientation": 4.351,
    "complex_problem_solving": 3.912,
    "operations_analysis": 2.947,
    "technology_design": 2.86,
    "equipment_selection": 3.596,
    "installation": 2.719,
    "programming": 1.632,
    "operations_monitoring": 1.298,
    "operation_and_control": 1.877,
    "equipment_maintenance": 1.825,
    "troubleshooting": 1.632,
    "repairing": 1.579,
    "quality_control_analysis": 1.684,
    "judgment_decision_making": 2.684,
    "systems_analysis": 2.386,
    "systems_evaluation": 1.965,
    "time_management": 3.474,
    "financial_resources_management": 1.368,
    "material_resources_management": 1.526,
    "personnel_resources_management": 2.246
  },
  "knowledge": {
    "business_management": 1.447,
    "clerical": 2.255,
    "economics_accounting": 0.787,
    "sales_marketing": 0.851,
    "customer_personal_service": 2.787,
    "personnel_hr": 1.383,
    "transportation": 0.362,
    "production_processing": 0.468,
    "agriculture_livestock": 0.34,
    "engineering": 0.489,
    "computers_electronics": 0.66,
    "design": 0.447,
    "building_construction": 0.447,
    "mechanical": 0.447,
    "mathematics_kn": 0.872,
    "physics": 1.213,
    "chemistry": 0.702,
    "biology": 2.255,
    "psychology": 2.979,
    "sociology": 2.298,
    "geography": 0.681,
    "medicine_dentistry": 3.915,
    "therapy_counseling": 3.851,
    "education_training_kn": 2.66,
    "japanese_language": 1.915,
    "foreign_language_kn": 0.723,
    "fine_arts": 1.064,
    "history_archaeology": 0.766,
    "philosophy_theology": 0.809,
    "public_safety_security": 1.234,
    "law_government": 0.851,
    "telecommunications": 0.681,
    "communications_media": 1.745
  },
  "abilities": {
    "oral_comprehension": 3.492,
    "written_comprehension": 3.426,
    "oral_expression": 3.607,
    "written_expression": 3.475,
    "fluency_of_ideas": 3.377,
    "originality": 3.246,
    "problem_sensitivity": 3.721,
    "deductive_reasoning": 3.295,
    "inductive_reasoning": 3.311,
    "information_ordering": 3.18,
    "category_flexibility": 3.098,
    "mathematical_reasoning": 2.246,
    "number_facility": 2.279,
    "memorization": 3.082,
    "perceptual_speed": 2.902,
    "spatial_orientation": 3.066,
    "visualization": 3.066,
    "selective_attention": 3.426,
    "time_sharing": 3.525,
    "arm_hand_steadiness": 3.426,
    "manual_dexterity": 3.246,
    "finger_dexterity": 3.262,
    "reaction_time": 3.443,
    "wrist_finger_speed": 3.016,
    "speed_of_limb_movement": 2.967,
    "static_strength": 3.311,
    "stamina": 3.311,
    "gross_body_equilibrium": 3.295,
    "near_vision": 2.967,
    "far_vision": 2.951,
    "visual_color_discrimination": 2.984,
    "depth_perception": 3.0,
    "hearing_sensitivity": 2.951,
    "auditory_attention": 3.115,
    "speech_clarity": 3.344
  },
  "work_characteristics": {
    "contact_with_others": 4.723,
    "face_to_face_discussions": 4.277,
    "telephone_communication": 3.745,
    "business_writing": 3.532,
    "conflict_situations": 2.979,
    "time_pressure": 3.383,
    "teamwork": 4.213,
    "dealing_with_external_customers": 3.787,
    "coordinate_lead_others": 3.894,
    "exactness_accuracy": 4.149,
    "repetitive_tasks": 3.426,
    "pace_determined_by_machine": 2.745,
    "responsibility_for_outcomes": 3.532,
    "indoor_climate_controlled": 4.617,
    "indoor_non_climate_controlled": 2.191,
    "outdoor_work": 2.915,
    "sitting": 2.66,
    "standing": 3.574,
    "repetition_of_activities": 2.702,
    "consequence_of_error": 3.532,
    "freedom_to_make_decisions": 3.574,
    "set_own_goals": 3.617,
    "regular_schedule": 0.702,
    "irregular_schedule": 0.234,
    "seasonal_schedule": 0.064,
    "email_communication": 3.213,
    "cramped_uncomfortable": 2.319,
    "disease_infection_risk": 4.447,
    "minor_injury_risk": 2.106,
    "standard_protective_equipment": 2.255,
    "specialized_protective_equipment": 1.553,
    "dealing_with_violent_people": 2.723,
    "walking_running": 3.319,
    "handling_objects_tools": 3.0,
    "physical_proximity": 4.596,
    "work_automation": 1.638,
    "responsibility_for_safety": 4.191,
    "impact_of_decisions": 3.255,
    "level_of_competition": 1.894
  },
  "work_activities": {
    "getting_information": 3.508,
    "monitor_processes": 3.541,
    "identifying_objects": 3.443,
    "inspecting_equipment": 2.787,
    "estimating_quantifiable": 2.934,
    "judging_quality": 3.082,
    "evaluating_compliance": 3.197,
    "processing_information": 3.082,
    "analyzing_data": 3.295,
    "making_decisions": 3.59,
    "thinking_creatively": 3.328,
    "updating_knowledge": 3.721,
    "developing_objectives": 3.738,
    "scheduling_work": 3.475,
    "organizing_planning": 3.59,
    "physical_activities": 3.377,
    "handling_objects": 3.279,
    "controlling_machines": 2.492,
    "operating_vehicles": 2.213,
    "computer_work": 2.836,
    "drafting_specifications": 2.213,
    "repairing_mechanical": 2.082,
    "repairing_electronic": 2.098,
    "documenting_information": 3.082,
    "interpreting_information": 3.279,
    "communicating_inside": 3.672,
    "communicating_outside": 3.508,
    "building_relationships": 3.607,
    "assisting_caring": 3.82,
    "selling_influencing": 3.115,
    "resolving_conflicts": 3.18,
    "performing_for_public": 2.869,
    "coordinating_others": 3.131,
    "developing_teams": 3.459,
    "training_teaching": 3.311,
    "guiding_subordinates": 3.164,
    "coaching_developing": 2.951,
    "providing_consultation": 2.574,
    "performing_administrative": 3.033,
    "staffing_organizational": 2.59,
    "monitoring_resources": 2.656
  },
  "education_distribution": {
    "below_high_school": 0.0,
    "high_school": 0.0,
    "vocational_school": 0.66,
    "junior_college": 0.0,
    "technical_college": 0.021,
    "university": 0.681,
    "masters": 0.106,
    "doctorate": 0.043,
    "unknown": 0.021
  },
  "training_pre": {
    "not_required": 0.255,
    "up_to_1_month": 0.021,
    "1_to_6_months": 0.106,
    "6_months_to_1_year": 0.064,
    "1_to_2_years": 0.043,
    "2_to_3_years": 0.106,
    "3_to_5_years": 0.319,
    "5_to_10_years": 0.0,
    "over_10_years": 0.0,
    "unknown": 0.085
  },
  "training_post": {
    "not_required": 0.0,
    "up_to_1_month": 0.0,
    "1_to_6_months": 0.213,
    "6_months_to_1_year": 0.17,
    "1_to_2_years": 0.234,
    "2_to_3_years": 0.149,
    "3_to_5_years": 0.128,
    "5_to_10_years": 0.0,
    "over_10_years": 0.0,
    "unknown": 0.106
  },
  "experience": {
    "not_required": 0.383,
    "up_to_1_month": 0.021,
    "1_to_6_months": 0.128,
    "6_months_to_1_year": 0.191,
    "1_to_2_years": 0.0,
    "2_to_3_years": 0.043,
    "3_to_5_years": 0.064,
    "5_to_10_years": 0.0,
    "over_10_years": 0.0,
    "unknown": 0.17
  },
  "employment_type": {
    "regular_employee": 0.957,
    "part_time": 0.213,
    "dispatched": 0.085,
    "contract": 0.085,
    "self_employed_freelance": 0.085,
    "executive": 0.043,
    "casual_non_student": 0.021,
    "casual_student": 0.043,
    "unknown": 0.0,
    "other": 0.0
  },
  "tasks_lead_ja": "身体や精神に障害がある人が心身の機能を回復し、日常生活や社会に復帰できるよう作業療法を用いて訓練を行う。",
  "tasks": [
    {
      "task_id": 1,
      "description_ja": "病院・施設・地域における作業療法のプログラムを企画・運営する。",
      "execution_rate": 0.902,
      "importance": 3.636
    },
    {
      "task_id": 2,
      "description_ja": "医師、看護師、理学療法士などからなるチームで、治療訓練の目標を決める。",
      "execution_rate": 0.984,
      "importance": 3.867
    },
    {
      "task_id": 3,
      "description_ja": "患者の身体機能、認知機能や日常生活動作の能力について観察や検査を行い、問題点を明らかにする。",
      "execution_rate": 0.984,
      "importance": 4.017
    },
    {
      "task_id": 4,
      "description_ja": "患者の希望と生活環境に応じて訓練する作業を選択し、組み合わせる。",
      "execution_rate": 0.984,
      "importance": 3.95
    },
    {
      "task_id": 5,
      "description_ja": "作業療法に使用する器具の使用前の準備や使用後の片付けをする。",
      "execution_rate": 0.984,
      "importance": 3.5
    },
    {
      "task_id": 6,
      "description_ja": "作業に使用する資材や装置を設計・改善する。",
      "execution_rate": 0.885,
      "importance": 3.296
    },
    {
      "task_id": 7,
      "description_ja": "プログラムの実施状況や障害の改善状況を記録し、管理する。",
      "execution_rate": 0.984,
      "importance": 3.817
    },
    {
      "task_id": 8,
      "description_ja": "患者の心理面をケアする。",
      "execution_rate": 0.984,
      "importance": 3.683
    },
    {
      "task_id": 9,
      "description_ja": "活動への参加に必要な技術や技能を指導し、障害の改善状況を評価する。",
      "execution_rate": 0.984,
      "importance": 3.817
    },
    {
      "task_id": 10,
      "description_ja": "他のスタッフや実習学生の指導やフォローを行う。",
      "execution_rate": 0.82,
      "importance": 3.24
    },
    {
      "task_id": 11,
      "description_ja": "地域やケアマネジャーと情報共有し、連携してケアにあたる。",
      "execution_rate": 0.885,
      "importance": 3.574
    },
    {
      "task_id": 12,
      "description_ja": "患者の家族の相談に応じ、必要な支援をする。",
      "execution_rate": 0.951,
      "importance": 3.621
    },
    {
      "task_id": 13,
      "description_ja": "ショック状態以前の患者の状態を把握する。",
      "execution_rate": 0.902,
      "importance": 3.455
    },
    {
      "task_id": 14,
      "description_ja": "患者の状況を医師に伝える。",
      "execution_rate": 0.951,
      "importance": 3.672
    },
    {
      "task_id": 15,
      "description_ja": "イベントやレクリエーション、机上課題を企画し、実行する。",
      "execution_rate": 0.836,
      "importance": 3.255
    },
    {
      "task_id": 16,
      "description_ja": "勉強会に参加し、知識やスキルを向上させる。",
      "execution_rate": 0.869,
      "importance": 3.358
    },
    {
      "task_id": 17,
      "description_ja": "レセプトを保存・管理する。",
      "execution_rate": 0.836,
      "importance": 3.235
    },
    {
      "task_id": 18,
      "description_ja": "行政に必要な支援の充実を働きかける。",
      "execution_rate": 0.787,
      "importance": 3.167
    },
    {
      "task_id": 19,
      "description_ja": "養成校での講師を担当し、学生指導や広報を行う。",
      "execution_rate": 0.623,
      "importance": 2.868
    }
  ],
  "related_orgs": [
    {
      "name_ja": "一般社団法人　日本作業療法士協会",
      "url": "http://www.jaot.or.jp/"
    }
  ],
  "related_certs_ja": [
    "作業療法士",
    "理学療法士",
    "認定作業療法士",
    "専門作業療法士"
  ],
  "url": "https://shigoto.mhlw.go.jp/User/Occupation/Detail/168",
  "data_source_versions": {
    "ipd_numeric": "v7.00",
    "ipd_description": "v7.00",
    "ipd_retrieved_at": "2026-05-04"
  },
  "last_updated_per_section": {
    "ipd_id": 2018,
    "classifications": 2022,
    "description": 2019
  }
}
