[
  {
    "sector_id": "iryo",
    "ja": "医療・保健",
    "occupation_count": 36,
    "ja_url": "https://mirai-shigoto.com/ja/sectors/iryo"
  },
  {
    "sector_id": "fukushi",
    "ja": "福祉・介護",
    "occupation_count": 15,
    "ja_url": "https://mirai-shigoto.com/ja/sectors/fukushi"
  },
  {
    "sector_id": "kyoiku",
    "ja": "教育・指導",
    "occupation_count": 20,
    "ja_url": "https://mirai-shigoto.com/ja/sectors/kyoiku"
  },
  {
    "sector_id": "hoan",
    "ja": "保安・公安",
    "occupation_count": 15,
    "ja_url": "https://mirai-shigoto.com/ja/sectors/hoan"
  },
  {
    "sector_id": "noringyo",
    "ja": "農林・水産",
    "occupation_count": 14,
    "ja_url": "https://mirai-shigoto.com/ja/sectors/noringyo"
  },
  {
    "sector_id": "senmon",
    "ja": "専門・技術",
    "occupation_count": 51,
    "ja_url": "https://mirai-shigoto.com/ja/sectors/senmon"
  },
  {
    "sector_id": "it",
    "ja": "IT・通信",
    "occupation_count": 22,
    "ja_url": "https://mirai-shigoto.com/ja/sectors/it"
  },
  {
    "sector_id": "shigyo",
    "ja": "士業・経営・コンサル",
    "occupation_count": 63,
    "ja_url": "https://mirai-shigoto.com/ja/sectors/shigyo"
  },
  {
    "sector_id": "creative",
    "ja": "クリエイティブ・メディア",
    "occupation_count": 37,
    "ja_url": "https://mirai-shigoto.com/ja/sectors/creative"
  },
  {
    "sector_id": "jimu",
    "ja": "事務・公務",
    "occupation_count": 57,
    "ja_url": "https://mirai-shigoto.com/ja/sectors/jimu"
  },
  {
    "sector_id": "hanbai",
    "ja": "販売・営業",
    "occupation_count": 41,
    "ja_url": "https://mirai-shigoto.com/ja/sectors/hanbai"
  },
  {
    "sector_id": "service",
    "ja": "サービス・接客",
    "occupation_count": 41,
    "ja_url": "https://mirai-shigoto.com/ja/sectors/service"
  },
  {
    "sector_id": "seizo",
    "ja": "製造・職人",
    "occupation_count": 59,
    "ja_url": "https://mirai-shigoto.com/ja/sectors/seizo"
  },
  {
    "sector_id": "maint",
    "ja": "設備・保守",
    "occupation_count": 49,
    "ja_url": "https://mirai-shigoto.com/ja/sectors/maint"
  },
  {
    "sector_id": "kensetu",
    "ja": "建設・土木",
    "occupation_count": 20,
    "ja_url": "https://mirai-shigoto.com/ja/sectors/kensetu"
  },
  {
    "sector_id": "keiseki",
    "ja": "軽作業・清掃",
    "occupation_count": 16,
    "ja_url": "https://mirai-shigoto.com/ja/sectors/keiseki"
  }
]