{"id":448,"title_ja":"医薬品販売/登録販売者","tasks_lead_ja":"薬局、ドラッグストア等で市販されている医薬品を販売する。","tasks":[{"task_id":1,"description_ja":"店内ミーティングをする。","execution_rate":0.737,"importance":2.738,"ai_risk":null,"ai_rationale_ja":null,"scored_by":null,"scored_at":null},{"task_id":2,"description_ja":"開店の準備（品出し、レジ開けや釣り銭の管理）をする。","execution_rate":0.842,"importance":3.521,"ai_risk":null,"ai_rationale_ja":null,"scored_by":null,"scored_at":null},{"task_id":3,"description_ja":"医薬品の効能や副作用について説明し、販売する。","execution_rate":0.947,"importance":3.926,"ai_risk":null,"ai_rationale_ja":null,"scored_by":null,"scored_at":null},{"task_id":4,"description_ja":"搬入された医薬品の受け取り、指示された医薬品の品出しをする。","execution_rate":0.912,"importance":3.538,"ai_risk":null,"ai_rationale_ja":null,"scored_by":null,"scored_at":null},{"task_id":5,"description_ja":"商品陳列の整理と商品の補充をする。","execution_rate":0.947,"importance":3.481,"ai_risk":null,"ai_rationale_ja":null,"scored_by":null,"scored_at":null},{"task_id":6,"description_ja":"在庫管理（PC管理、目視による店頭商品在庫のチェック）をする。","execution_rate":0.93,"importance":3.453,"ai_risk":null,"ai_rationale_ja":null,"scored_by":null,"scored_at":null},{"task_id":7,"description_ja":"医薬品や商品を発注する。","execution_rate":0.912,"importance":3.385,"ai_risk":null,"ai_rationale_ja":null,"scored_by":null,"scored_at":null},{"task_id":8,"description_ja":"業務内容について日誌の作成をする。","execution_rate":0.719,"importance":2.854,"ai_risk":null,"ai_rationale_ja":null,"scored_by":null,"scored_at":null},{"task_id":9,"description_ja":"商品の表示価格を確認する。","execution_rate":0.947,"importance":3.352,"ai_risk":null,"ai_rationale_ja":null,"scored_by":null,"scored_at":null},{"task_id":10,"description_ja":"季節や需要に応じて、商品の陳列を工夫する。","execution_rate":0.912,"importance":3.327,"ai_risk":null,"ai_rationale_ja":null,"scored_by":null,"scored_at":null},{"task_id":11,"description_ja":"サプリや青汁などの実演や、サンプリングの提供を行う。","execution_rate":0.807,"importance":2.674,"ai_risk":null,"ai_rationale_ja":null,"scored_by":null,"scored_at":null},{"task_id":12,"description_ja":"POPなど企画提案をする。","execution_rate":0.754,"importance":2.512,"ai_risk":null,"ai_rationale_ja":null,"scored_by":null,"scored_at":null},{"task_id":13,"description_ja":"商品の期限や品質を管理する。","execution_rate":0.965,"importance":3.927,"ai_risk":null,"ai_rationale_ja":null,"scored_by":null,"scored_at":null},{"task_id":14,"description_ja":"顧客管理をする。","execution_rate":0.825,"importance":2.894,"ai_risk":null,"ai_rationale_ja":null,"scored_by":null,"scored_at":null},{"task_id":15,"description_ja":"経理業務をする。","execution_rate":0.667,"importance":2.763,"ai_risk":null,"ai_rationale_ja":null,"scored_by":null,"scored_at":null},{"task_id":16,"description_ja":"商品情報の収集や共有を行う。","execution_rate":0.93,"importance":3.245,"ai_risk":null,"ai_rationale_ja":null,"scored_by":null,"scored_at":null},{"task_id":17,"description_ja":"薬剤師の業務を補助する。","execution_rate":0.719,"importance":2.78,"ai_risk":null,"ai_rationale_ja":null,"scored_by":null,"scored_at":null},{"task_id":18,"description_ja":"店内外の清掃や整理をする。","execution_rate":0.93,"importance":3.113,"ai_risk":null,"ai_rationale_ja":null,"scored_by":null,"scored_at":null}]}
