{"id":531,"title_ja":"キッティング作業員（PCセットアップ作業員）","tasks_lead_ja":"パソコン（ＰＣ）やタブレットなどのＩＴ機器をユーザーがすぐに業務に使えるようセットアップする作業（「キッティング」という）を行う。","tasks":[{"task_id":1,"description_ja":"機器を開梱・通電し、モニターやマウスなど周辺機器を接続する。","execution_rate":0.947,"importance":2.944,"ai_risk":null,"ai_rationale_ja":null,"scored_by":null,"scored_at":null},{"task_id":2,"description_ja":"システムセットアップ、OSのインストールを行う。","execution_rate":0.974,"importance":3.432,"ai_risk":null,"ai_rationale_ja":null,"scored_by":null,"scored_at":null},{"task_id":3,"description_ja":"初期設定、アカウント設定を行う。","execution_rate":1,"importance":3.658,"ai_risk":null,"ai_rationale_ja":null,"scored_by":null,"scored_at":null},{"task_id":4,"description_ja":"ネットワークに接続する。","execution_rate":1,"importance":3.816,"ai_risk":null,"ai_rationale_ja":null,"scored_by":null,"scored_at":null},{"task_id":5,"description_ja":"業務アプリケーションやセキュリティソフトをインストールする。","execution_rate":1,"importance":3.342,"ai_risk":null,"ai_rationale_ja":null,"scored_by":null,"scored_at":null},{"task_id":6,"description_ja":"各種設定の動作確認を行う。","execution_rate":1,"importance":3.579,"ai_risk":null,"ai_rationale_ja":null,"scored_by":null,"scored_at":null},{"task_id":7,"description_ja":"動作確認で問題がなければ機器に管理シール等を貼り、管理台帳などへ登録する。","execution_rate":0.921,"importance":3.286,"ai_risk":null,"ai_rationale_ja":null,"scored_by":null,"scored_at":null},{"task_id":8,"description_ja":"動作のトラブル等が生じた場合はチームリーダー等と相談して解決を図る。","execution_rate":0.947,"importance":3.5,"ai_risk":null,"ai_rationale_ja":null,"scored_by":null,"scored_at":null},{"task_id":9,"description_ja":"１台分の作業が終了すれば、続けて次の機器の作業を行う。","execution_rate":1,"importance":3.421,"ai_risk":null,"ai_rationale_ja":null,"scored_by":null,"scored_at":null},{"task_id":10,"description_ja":"インストール等、時間のかかる作業を同時並行で複数台行う。","execution_rate":1,"importance":3.526,"ai_risk":null,"ai_rationale_ja":null,"scored_by":null,"scored_at":null},{"task_id":11,"description_ja":"必要に応じて社外から社内システムへ接続するネットワーク設定作業を行う。","execution_rate":0.921,"importance":3.229,"ai_risk":null,"ai_rationale_ja":null,"scored_by":null,"scored_at":null}]}
